HISTORY.rst
voting/__init__.py
voting/_version.py
voting/apportionment.py
voting/diversity.py
voting/proportion.py
voting/quota.py
voting/util.py
voting-0.1.3.dist-info/LICENSE.txt
voting-0.1.3.dist-info/WHEEL
voting-0.1.3.dist-info/METADATA
voting-0.1.3.dist-info/RECORD
